[{"title":"Russ Conway","nid":"4359","type":"finalist","changed":1438981220,"path_alias":"finalists\/russ-conway","field_abbr_citation":{"und":[{"safe_value":"For his reporting about questionable business practices in professional hockey.\n"}]},"field_category":{"und":[{"tid":"278"}]},"field_location_text":{"und":[{"safe_value":"Lawrence, MA\n"}]},"field_publication":{"und":[{"safe_value":"The Eagle-Tribune\n"}]},"field_publisher":[],"field_year":{"und":[{"tid":"128"}]}},{"title":"Gregg Jones","nid":"4360","type":"finalist","changed":1438981220,"path_alias":"finalists\/gregg-jones","field_abbr_citation":{"und":[{"safe_value":"For stories about the state\u0026#039;s faltering rural health-care system.\n"}]},"field_category":{"und":[{"tid":"278"}]},"field_location_text":{"und":[{"safe_value":"(now defunct) Little Rock, AR\n"}]},"field_publication":{"und":[{"safe_value":"Arkansas Gazette\n"}]},"field_publisher":[],"field_year":{"und":[{"tid":"128"}]}},{"title":"Michael Shelden","nid":"4361","type":"finalist","changed":1438981220,"path_alias":"finalists\/michael-shelden","field_abbr_citation":[],"field_category":{"und":[{"tid":"222"}]},"field_location_text":[],"field_publication":{"und":[{"safe_value":"Orwell: The Authorized Biography\n"}]},"field_publisher":{"und":[{"safe_value":"HarperCollins\n"}]},"field_year":{"und":[{"tid":"128"}]}},{"title":"William S. McFeely","nid":"4362","type":"finalist","changed":1438981222,"path_alias":"finalists\/william-s-mcfeely","field_abbr_citation":[],"field_category":{"und":[{"tid":"222"}]},"field_location_text":[],"field_publication":{"und":[{"safe_value":"Frederick Douglass\n"}]},"field_publisher":{"und":[{"safe_value":"W.W. Norton \u0026amp; Company\n"}]},"field_year":{"und":[{"tid":"128"}]}},{"title":"Liz Balmaseda","nid":"4363","type":"finalist","changed":1438981222,"path_alias":"finalists\/liz-balmaseda","field_abbr_citation":{"und":[{"safe_value":"For her columns about local Cuban-Americans and the issues affecting the immigrant community.\n"}]},"field_category":{"und":[{"tid":"212"}]},"field_location_text":[],"field_publication":{"und":[{"safe_value":"The Miami Herald\n"}]},"field_publisher":[],"field_year":{"und":[{"tid":"128"}]}},{"title":"Robert Lipsyte","nid":"4364","type":"finalist","changed":1438981222,"path_alias":"finalists\/robert-lipsyte","field_abbr_citation":{"und":[{"safe_value":"For his insightful commentary on the world of sports.\n"}]},"field_category":{"und":[{"tid":"212"}]},"field_location_text":[],"field_publication":{"und":[{"safe_value":"The New York Times\n"}]},"field_publisher":[],"field_year":{"und":[{"tid":"128"}]}},{"title":"Michael Feingold","nid":"4365","type":"finalist","changed":1438981222,"path_alias":"finalists\/michael-feingold","field_abbr_citation":{"und":[{"safe_value":"For his theater reviews.\n"}]},"field_category":{"und":[{"tid":"213"}]},"field_location_text":{"und":[{"safe_value":"the New York City weekly\n"}]},"field_publication":{"und":[{"safe_value":"The Village Voice\n"}]},"field_publisher":[],"field_year":{"und":[{"tid":"128"}]}},{"title":"Itabari Njeri","nid":"4366","type":"finalist","changed":1438981222,"path_alias":"finalists\/itabari-njeri","field_abbr_citation":{"und":[{"safe_value":"For her essay on race and the messages of black nationalism.\n"}]},"field_category":{"und":[{"tid":"213"}]},"field_location_text":[],"field_publication":{"und":[{"safe_value":"Los Angeles Times\n"}]},"field_publisher":[],"field_year":{"und":[{"tid":"128"}]}},{"title":"Leslie Savan","nid":"4367","type":"finalist","changed":1438981222,"path_alias":"finalists\/leslie-savan-0","field_abbr_citation":{"und":[{"safe_value":"For her critical columns on advertising and the media.\n"}]},"field_category":{"und":[{"tid":"213"}]},"field_location_text":{"und":[{"safe_value":"the New York City weekly\n"}]},"field_publication":{"und":[{"safe_value":"The Village Voice\n"}]},"field_publisher":[],"field_year":{"und":[{"tid":"128"}]}},{"title":"David Feldshuh","nid":"4368","type":"finalist","changed":1438981222,"path_alias":"finalists\/david-feldshuh","field_abbr_citation":[],"field_category":{"und":[{"tid":"218"}]},"field_location_text":[],"field_publication":{"und":[{"safe_value":"Miss Evers\u0026#039; Boys\n"}]},"field_publisher":[],"field_year":{"und":[{"tid":"128"}]}},{"title":"August Wilson","nid":"4369","type":"finalist","changed":1438981222,"path_alias":"finalists\/august-wilson-0","field_abbr_citation":[],"field_category":{"und":[{"tid":"218"}]},"field_location_text":[],"field_publication":{"und":[{"safe_value":"Two Trains Running\n"}]},"field_publisher":[],"field_year":{"und":[{"tid":"128"}]}},{"title":"Herb Gardner","nid":"4370","type":"finalist","changed":1438981222,"path_alias":"finalists\/herb-gardner","field_abbr_citation":[],"field_category":{"und":[{"tid":"218"}]},"field_location_text":[],"field_publication":{"und":[{"safe_value":"Conversations With My Father\n"}]},"field_publisher":[],"field_year":{"und":[{"tid":"128"}]}},{"title":"Donald Margulies","nid":"4371","type":"finalist","changed":1438981222,"path_alias":"finalists\/donald-margulies","field_abbr_citation":[],"field_category":{"und":[{"tid":"218"}]},"field_location_text":[],"field_publication":{"und":[{"safe_value":"Sight Unseen\n"}]},"field_publisher":[],"field_year":{"und":[{"tid":"128"}]}},{"title":"Steve Benson","nid":"4372","type":"finalist","changed":1438981222,"path_alias":"finalists\/steve-benson-1","field_abbr_citation":[],"field_category":{"und":[{"tid":"215"}]},"field_location_text":{"und":[{"safe_value":"Tacoma, WA\n"}]},"field_publication":{"und":[{"safe_value":"Morning News Tribune and the Arizona Republic\n"}]},"field_publisher":[],"field_year":{"und":[{"tid":"128"}]}},{"title":"Ralph Dunagin","nid":"4373","type":"finalist","changed":1438981222,"path_alias":"finalists\/ralph-dunagin-0","field_abbr_citation":[],"field_category":{"und":[{"tid":"215"}]},"field_location_text":[],"field_publication":{"und":[{"safe_value":"Orlando (FL) Sentinel\n"}]},"field_publisher":[],"field_year":{"und":[{"tid":"128"}]}},{"title":"Robert J. Gaydos","nid":"4374","type":"finalist","changed":1438981222,"path_alias":"finalists\/robert-j-gaydos","field_abbr_citation":{"und":[{"safe_value":"For his editorials on a variety of local and national issues.\n"}]},"field_category":{"und":[{"tid":"214"}]},"field_location_text":{"und":[{"safe_value":"Middletown, NY\n"}]},"field_publication":{"und":[{"safe_value":"Times Herald-Record\n"}]},"field_publisher":[],"field_year":{"und":[{"tid":"128"}]}},{"title":"Henry Bryan","nid":"4375","type":"finalist","changed":1438981222,"path_alias":"finalists\/henry-bryan","field_abbr_citation":{"und":[{"safe_value":"For his editorial campaign urging state support of the Southeastern Pennsylvania Transit System, the fourth largest mass-transit system in the nation.\n"}]},"field_category":{"und":[{"tid":"214"}]},"field_location_text":[],"field_publication":{"und":[{"safe_value":"The Philadelphia Inquirer\n"}]},"field_publisher":[],"field_year":{"und":[{"tid":"128"}]}},{"title":"James O\u0027Byrne, Mark Schleifstein and G. Andrew Boyd","nid":"4376","type":"finalist","changed":1438981222,"path_alias":"finalists\/james-obyrne-mark-schleifstein-and-g-andrew-boyd","field_abbr_citation":{"und":[{"safe_value":"For \u0026quot;Louisiana in Peril,\u0026quot; articles about the toxic waste and pollution that threaten the future of the state.\n"}]},"field_category":{"und":[{"tid":"264"}]},"field_location_text":{"und":[{"safe_value":"New Orleans, LA\n"}]},"field_publication":{"und":[{"safe_value":"Times-Picayune\n"}]},"field_publisher":[],"field_year":{"und":[{"tid":"128"}]}},{"title":"Rob Carson, Geff Hinds and Suki Dardarian","nid":"4377","type":"finalist","changed":1438981222,"path_alias":"finalists\/rob-carson-geff-hinds-and-suki-dardarian","field_abbr_citation":{"und":[{"safe_value":"For comprehensive coverage of a controversial and ultimately unsuccessful special initiative on the state\u0026#039;s 1991 ballot that would have granted terminally ill individuals the right to have a physician end their lives.\n"}]},"field_category":{"und":[{"tid":"264"}]},"field_location_text":{"und":[{"safe_value":"Tacoma, WA\n"}]},"field_publication":{"und":[{"safe_value":"Morning News Tribune\n"}]},"field_publisher":[],"field_year":{"und":[{"tid":"128"}]}},{"title":"Paul Kuroda","nid":"4378","type":"finalist","changed":1438981222,"path_alias":"finalists\/paul-kuroda","field_abbr_citation":{"und":[{"safe_value":"For his photographs of the dangerous journey of illegal immigrants across the U.S.-Mexican border.\n"}]},"field_category":{"und":[{"tid":"217"}]},"field_location_text":{"und":[{"safe_value":"Santa Ana, CA\n"}]},"field_publication":{"und":[{"safe_value":"Orange County Register\n"}]},"field_publisher":[],"field_year":{"und":[{"tid":"128"}]}},{"title":"Bill Snead","nid":"4379","type":"finalist","changed":1438981222,"path_alias":"finalists\/bill-snead","field_abbr_citation":{"und":[{"safe_value":"For his photographs depicting the harshness and misery of the Kurdish refugee camps.\n"}]},"field_category":{"und":[{"tid":"217"}]},"field_location_text":[],"field_publication":{"und":[{"safe_value":"The Washington Post\n"}]},"field_publisher":[],"field_year":{"und":[{"tid":"128"}]}},{"title":"Frank Bruni","nid":"4380","type":"finalist","changed":1438981222,"path_alias":"finalists\/frank-bruni","field_abbr_citation":{"und":[{"safe_value":"For his profile of a child molester that challenged many assumptions about sexual abuse.\n"}]},"field_category":{"und":[{"tid":"211"}]},"field_location_text":[],"field_publication":{"und":[{"safe_value":"Detroit Free Press\n"}]},"field_publisher":[],"field_year":{"und":[{"tid":"128"}]}},{"title":"Sheryl James","nid":"4381","type":"finalist","changed":1438981222,"path_alias":"finalists\/sheryl-james","field_abbr_citation":{"und":[{"safe_value":"For her gripping account of the effort to transplant the organs of a dead boy and turn the tragedy of his death into a gift of life for others.\n"}]},"field_category":{"und":[{"tid":"211"}]},"field_location_text":[],"field_publication":{"und":[{"safe_value":"St. Petersburg Times\n"}]},"field_publisher":[],"field_year":{"und":[{"tid":"128"}]}},{"title":"Don DeLillo","nid":"4382","type":"finalist","changed":1438981222,"path_alias":"finalists\/don-delillo","field_abbr_citation":[],"field_category":{"und":[{"tid":"219"}]},"field_location_text":[],"field_publication":{"und":[{"safe_value":"Mao II\n"}]},"field_publisher":{"und":[{"safe_value":"Viking\n"}]},"field_year":{"und":[{"tid":"128"}]}},{"title":"David Gates","nid":"4383","type":"finalist","changed":1438981222,"path_alias":"finalists\/david-gates","field_abbr_citation":[],"field_category":{"und":[{"tid":"219"}]},"field_location_text":[],"field_publication":{"und":[{"safe_value":"Jernigan\n"}]},"field_publisher":{"und":[{"safe_value":"Alfred A. Knopf\n"}]},"field_year":{"und":[{"tid":"128"}]}},{"title":"Robert M. Pirsig","nid":"4384","type":"finalist","changed":1438981222,"path_alias":"finalists\/robert-m-pirsig","field_abbr_citation":[],"field_category":{"und":[{"tid":"219"}]},"field_location_text":[],"field_publication":{"und":[{"safe_value":"Lila: An Inquiry into Morals\n"}]},"field_publisher":{"und":[{"safe_value":"Bantam Books\n"}]},"field_year":{"und":[{"tid":"128"}]}},{"title":"Andre Dubus","nid":"4385","type":"finalist","changed":1438981222,"path_alias":"finalists\/andre-dubus","field_abbr_citation":[],"field_category":{"und":[{"tid":"223"}]},"field_location_text":[],"field_publication":{"und":[{"safe_value":"Broken Vessels\n"}]},"field_publisher":{"und":[{"safe_value":"David R. Godine\n"}]},"field_year":{"und":[{"tid":"128"}]}},{"title":"Thomas Byrne Edsall and Mary D. Edsall","nid":"4386","type":"finalist","changed":1438981222,"path_alias":"finalists\/thomas-byrne-edsall-and-mary-d-edsall","field_abbr_citation":[],"field_category":{"und":[{"tid":"223"}]},"field_location_text":[],"field_publication":{"und":[{"safe_value":"Chain Reaction: The Impact of Race, Rights, and Taxes on American Politics\n"}]},"field_publisher":{"und":[{"safe_value":"W.W. Norton \u0026amp; Company\n"}]},"field_year":{"und":[{"tid":"128"}]}},{"title":"William Cronon","nid":"4387","type":"finalist","changed":1438981222,"path_alias":"finalists\/william-cronon","field_abbr_citation":[],"field_category":{"und":[{"tid":"220"}]},"field_location_text":[],"field_publication":{"und":[{"safe_value":"Nature\u0026#039;s Metropolis: Chicago and the Great West\n"}]},"field_publisher":{"und":[{"safe_value":"W.W. Norton \u0026amp; Company\n"}]},"field_year":{"und":[{"tid":"128"}]}},{"title":"Theodore Draper","nid":"4388","type":"finalist","changed":1438981222,"path_alias":"finalists\/theodore-draper","field_abbr_citation":[],"field_category":{"und":[{"tid":"220"}]},"field_location_text":[],"field_publication":{"und":[{"safe_value":"A Very Thin Line: The Iran-Contra Affairs\n"}]},"field_publisher":{"und":[{"safe_value":"Hill \u0026amp; Wang\n"}]},"field_year":{"und":[{"tid":"128"}]}},{"title":"John Frederick Martin","nid":"4389","type":"finalist","changed":1438981222,"path_alias":"finalists\/john-frederick-martin","field_abbr_citation":[],"field_category":{"und":[{"tid":"220"}]},"field_location_text":[],"field_publication":{"und":[{"safe_value":"Profits in the Wilderness: Entrepreneurship and the Founding of New England Towns in the Seventeenth Century\n"}]},"field_publisher":{"und":[{"safe_value":"The University of North Carolina Press\n"}]},"field_year":{"und":[{"tid":"128"}]}},{"title":"Richard White","nid":"4390","type":"finalist","changed":1438981222,"path_alias":"finalists\/richard-white","field_abbr_citation":[],"field_category":{"und":[{"tid":"220"}]},"field_location_text":[],"field_publication":{"und":[{"safe_value":"The Middle Ground: Indians, Empires, and Republics in the Great Lakes Region, 1650-1815\n"}]},"field_publisher":{"und":[{"safe_value":"Cambridge University Press\n"}]},"field_year":{"und":[{"tid":"128"}]}},{"title":"Dudley Althaus","nid":"4391","type":"finalist","changed":1438981222,"path_alias":"finalists\/dudley-althaus","field_abbr_citation":{"und":[{"safe_value":"For his articles on the causes of the cholera epidemic in Peru and Mexico.\n"}]},"field_category":{"und":[{"tid":"210"}]},"field_location_text":[],"field_publication":{"und":[{"safe_value":"Houston Chronicle\n"}]},"field_publisher":[],"field_year":{"und":[{"tid":"128"}]}},{"title":"Staff","nid":"4392","type":"finalist","changed":1438981222,"path_alias":"finalists\/staff-54","field_abbr_citation":{"und":[{"safe_value":"For its vivid and comprehensive coverage of the Soviet Union\u0026#039;s collapse.\n"}]},"field_category":{"und":[{"tid":"210"}]},"field_location_text":[],"field_publication":{"und":[{"safe_value":"Los Angeles Times\n"}]},"field_publisher":[],"field_year":{"und":[{"tid":"128"}]}},{"title":"Jennifer Hyman","nid":"4393","type":"finalist","changed":1438981222,"path_alias":"finalists\/jennifer-hyman","field_abbr_citation":{"und":[{"safe_value":"For an investigation that revealed secret links between the Rochester Institute of Technology and the CIA.\n"}]},"field_category":{"und":[{"tid":"206"}]},"field_location_text":{"und":[{"safe_value":"Rochester, NY\n"}]},"field_publication":{"und":[{"safe_value":"Democrat and Chronicle\n"}]},"field_publisher":[],"field_year":{"und":[{"tid":"128"}]}},{"title":"Staff","nid":"4394","type":"finalist","changed":1438981222,"path_alias":"finalists\/staff-55","field_abbr_citation":{"und":[{"safe_value":"For its persistent investigation of financial abuses at a University of South Carolina foundation, which prompted significant reforms.\n"}]},"field_category":{"und":[{"tid":"206"}]},"field_location_text":[],"field_publication":{"und":[{"safe_value":"Greenville (SC) News\n"}]},"field_publisher":[],"field_year":{"und":[{"tid":"128"}]}},{"title":"Ralph Shapey","nid":"4395","type":"finalist","changed":1438981222,"path_alias":"finalists\/ralph-shapey-0","field_abbr_citation":{"und":[{"safe_value":"Premiered on November 21, 1992, by The Chicago Symphony Orchestra.\n"}]},"field_category":{"und":[{"tid":"225"}]},"field_location_text":[],"field_publication":{"und":[{"safe_value":"Concerto Fantastique\n"}]},"field_publisher":[],"field_year":{"und":[{"tid":"128"}]}},{"title":"Donald L. Barlett and James B. Steele","nid":"4396","type":"finalist","changed":1438981222,"path_alias":"finalists\/donald-l-barlett-and-james-b-steele","field_abbr_citation":{"und":[{"safe_value":"For their series \u0026quot;America: What Went Wrong?\u0026quot; which examined the public policy failures that have diminished the American middle class.\n"}]},"field_category":{"und":[{"tid":"209"}]},"field_location_text":[],"field_publication":{"und":[{"safe_value":"The Philadelphia Inquirer\n"}]},"field_publisher":[],"field_year":{"und":[{"tid":"128"}]}},{"title":"Maureen Dowd","nid":"4397","type":"finalist","changed":1438981222,"path_alias":"finalists\/maureen-dowd","field_abbr_citation":{"und":[{"safe_value":"For her coverage of national politics and its personalities.\n"}]},"field_category":{"und":[{"tid":"209"}]},"field_location_text":[],"field_publication":{"und":[{"safe_value":"The New York Times\n"}]},"field_publisher":[],"field_year":{"und":[{"tid":"128"}]}},{"title":"Robert Creeley","nid":"4398","type":"finalist","changed":1438981222,"path_alias":"finalists\/robert-creeley","field_abbr_citation":[],"field_category":{"und":[{"tid":"224"}]},"field_location_text":[],"field_publication":{"und":[{"safe_value":"Selected Poems\n"}]},"field_publisher":{"und":[{"safe_value":"University of California Press\n"}]},"field_year":{"und":[{"tid":"128"}]}},{"title":"Adrienne Rich","nid":"4399","type":"finalist","changed":1438981222,"path_alias":"finalists\/adrienne-rich-0","field_abbr_citation":[],"field_category":{"und":[{"tid":"224"}]},"field_location_text":[],"field_publication":{"und":[{"safe_value":"An Atlas of the Difficult World\n"}]},"field_publisher":{"und":[{"safe_value":"W.W. Norton \u0026amp; Company\n"}]},"field_year":{"und":[{"tid":"128"}]}},{"title":"Staff","nid":"4400","type":"finalist","changed":1438981222,"path_alias":"finalists\/staff-56","field_abbr_citation":{"und":[{"safe_value":"For extensive reporting by Mike Casey and Russell Carollo that revealed gross national neglect of worker safety conditions and regulations and prompted workplace-reform legislation.\n"}]},"field_category":{"und":[{"tid":"204"}]},"field_location_text":[],"field_publication":{"und":[{"safe_value":"Dayton (Ohio) Daily News\n"}]},"field_publisher":[],"field_year":{"und":[{"tid":"128"}]}},{"title":"Staff","nid":"4401","type":"finalist","changed":1438981222,"path_alias":"finalists\/staff-57","field_abbr_citation":{"und":[{"safe_value":"For articles exploring the causes and human consequences of the epidemic of gun violence in the capital area that claimed more than 3,000 lives in five years.\n"}]},"field_category":{"und":[{"tid":"204"}]},"field_location_text":[],"field_publication":{"und":[{"safe_value":"The Washington Post\n"}]},"field_publisher":[],"field_year":{"und":[{"tid":"128"}]}},{"title":"David C. Turnley","nid":"4402","type":"finalist","changed":1438981222,"path_alias":"finalists\/david-c-turnley-0","field_abbr_citation":{"und":[{"safe_value":"For a photograph from the Persian Gulf War of a grieving American soldier sitting by the body of a slain friend.\n"}]},"field_category":{"und":[{"tid":"274"}]},"field_location_text":[],"field_publication":{"und":[{"safe_value":"Detroit Free Press\n"}]},"field_publisher":[],"field_year":{"und":[{"tid":"128"}]}},{"title":"Staff","nid":"4403","type":"finalist","changed":1438981222,"path_alias":"finalists\/staff-58","field_abbr_citation":{"und":[{"safe_value":"For photographs of Albanian refugees stranded in Italy.\n"}]},"field_category":{"und":[{"tid":"274"}]},"field_location_text":[],"field_publication":{"und":[{"safe_value":"Associated Press\n"}]},"field_publisher":[],"field_year":{"und":[{"tid":"128"}]}},{"title":"Staff","nid":"4404","type":"finalist","changed":1438981222,"path_alias":"finalists\/staff-59","field_abbr_citation":{"und":[{"safe_value":"For its coverage of a helicopter crash in a local schoolyard that killed U.S. Senator John Heinz and six others.\n"}]},"field_category":{"und":[{"tid":"275"}]},"field_location_text":[],"field_publication":{"und":[{"safe_value":"The Philadelphia Inquirer\n"}]},"field_publisher":[],"field_year":{"und":[{"tid":"128"}]}},{"title":"Staff","nid":"4405","type":"finalist","changed":1438981222,"path_alias":"finalists\/staff-60","field_abbr_citation":{"und":[{"safe_value":"For its coverage of the destruction to the island community of Martha\u0026#039;s Vineyard by Hurricane Bob.\n"}]},"field_category":{"und":[{"tid":"275"}]},"field_location_text":{"und":[{"safe_value":"an Edgartown, MA weekly\n"}]},"field_publication":{"und":[{"safe_value":"Vineyard Gazette\n"}]},"field_publisher":[],"field_year":{"und":[{"tid":"128"}]}}]