[{"title":"Robert E. Sherwood","nid":"6009","type":"winner","changed":1439235134,"path_alias":"winners\/robert-e-sherwood-2","field_abbr_citation":[],"field_category":{"und":[{"tid":"222"}]},"field_location_text":[],"field_publication":{"und":[{"safe_value":"Roosevelt and Hopkins\n"}]},"field_publisher":{"und":[{"safe_value":"Harper\n"}]},"field_teaser_thumbnail":[],"field_year":{"und":[{"tid":"171"}]}},{"title":"Arthur Miller","nid":"6010","type":"winner","changed":1439235136,"path_alias":"winners\/arthur-miller","field_abbr_citation":[],"field_category":{"und":[{"tid":"218"}]},"field_location_text":[],"field_publication":{"und":[{"safe_value":"Death of a Salesman\n"}]},"field_publisher":[],"field_teaser_thumbnail":[],"field_year":{"und":[{"tid":"171"}]}},{"title":"Lute Pease","nid":"6011","type":"winner","changed":1439235136,"path_alias":"winners\/lute-pease","field_abbr_citation":{"und":[{"safe_value":"For \u0026quot;Who Me?\u0026quot;\n"}]},"field_category":{"und":[{"tid":"215"}]},"field_location_text":[],"field_publication":{"und":[{"safe_value":"Newark Evening News\n"}]},"field_publisher":[],"field_teaser_thumbnail":[],"field_year":{"und":[{"tid":"171"}]}},{"title":"Herbert Elliston","nid":"6012","type":"winner","changed":1534954698,"path_alias":"winners\/herbert-elliston","field_abbr_citation":{"und":[{"safe_value":"For distinguished editorial writing during the year.\r\n"}]},"field_category":{"und":[{"tid":"214"}]},"field_location_text":[],"field_publication":{"und":[{"safe_value":"The Washington Post"}]},"field_publisher":[],"field_teaser_thumbnail":[],"field_year":{"und":[{"tid":"171"}]}},{"title":"John H. Crider","nid":"6013","type":"winner","changed":1439235136,"path_alias":"winners\/john-h-crider","field_abbr_citation":{"und":[{"safe_value":"For distinguished editorial writing during the year.\n"}]},"field_category":{"und":[{"tid":"214"}]},"field_location_text":[],"field_publication":{"und":[{"safe_value":"The Boston Herald\n"}]},"field_publisher":[],"field_teaser_thumbnail":[],"field_year":{"und":[{"tid":"171"}]}},{"title":"James Gould Cozzens","nid":"6014","type":"winner","changed":1439235136,"path_alias":"winners\/james-gould-cozzens","field_abbr_citation":[],"field_category":{"und":[{"tid":"219"}]},"field_location_text":[],"field_publication":{"und":[{"safe_value":"Guard of Honor\n"}]},"field_publisher":{"und":[{"safe_value":"Harcourt\n"}]},"field_teaser_thumbnail":[],"field_year":{"und":[{"tid":"171"}]}},{"title":"Roy Franklin Nichols","nid":"6015","type":"winner","changed":1439235136,"path_alias":"winners\/roy-franklin-nichols","field_abbr_citation":[],"field_category":{"und":[{"tid":"220"}]},"field_location_text":[],"field_publication":{"und":[{"safe_value":"The Disruption of American Democracy\n"}]},"field_publisher":{"und":[{"safe_value":"Macmillan\n"}]},"field_teaser_thumbnail":[],"field_year":{"und":[{"tid":"171"}]}},{"title":"Price Day","nid":"6016","type":"winner","changed":1439235136,"path_alias":"winners\/price-day","field_abbr_citation":{"und":[{"safe_value":"For his series of 12 articles entitled, \u0026quot;Experiment in Freedom: India and Its First Year of Independence.\u0026quot;\n"}]},"field_category":{"und":[{"tid":"210"}]},"field_location_text":[],"field_publication":{"und":[{"safe_value":"The Baltimore Sun\n"}]},"field_publisher":[],"field_teaser_thumbnail":[],"field_year":{"und":[{"tid":"171"}]}},{"title":"Malcolm Johnson","nid":"6017","type":"winner","changed":1569854010,"path_alias":"winners\/malcolm-johnson","field_abbr_citation":{"und":[{"safe_value":"For his series of 24 articles entitled \u0026quot;Crime on the Waterfront\u0026quot; in New York City.\r\n"}]},"field_category":{"und":[{"tid":"208"}]},"field_location_text":[],"field_publication":{"und":[{"safe_value":"New York Sun"}]},"field_publisher":[],"field_teaser_thumbnail":[],"field_year":{"und":[{"tid":"171"}]}},{"title":"Virgil Thomson","nid":"6018","type":"winner","changed":1439235136,"path_alias":"winners\/virgil-thomson","field_abbr_citation":{"und":[{"safe_value":"Released in 1948 by Robert Flaherty Productions.\n"}]},"field_category":{"und":[{"tid":"225"}]},"field_location_text":[],"field_publication":{"und":[{"safe_value":"Music for the film Louisiana Story\n"}]},"field_publisher":[],"field_teaser_thumbnail":[],"field_year":{"und":[{"tid":"171"}]}},{"title":"C. P. Trussell","nid":"6019","type":"winner","changed":1439235136,"path_alias":"winners\/c-p-trussell","field_abbr_citation":{"und":[{"safe_value":"For consistent excellence covering the national scene from Washington.\n"}]},"field_category":{"und":[{"tid":"209"}]},"field_location_text":[],"field_publication":{"und":[{"safe_value":"The New York Times\n"}]},"field_publisher":[],"field_teaser_thumbnail":[],"field_year":{"und":[{"tid":"171"}]}},{"title":"Nathaniel Fein","nid":"6020","type":"winner","changed":1470680398,"path_alias":"winners\/nathaniel-fein","field_abbr_citation":{"und":[{"safe_value":"For his photo, \u0026quot;Babe Ruth Bows Out.\u0026quot;\r\n"}]},"field_category":{"und":[{"tid":"271"}]},"field_location_text":[],"field_publication":{"und":[{"safe_value":"New York Herald-Tribune"}]},"field_publisher":[],"field_teaser_thumbnail":[],"field_year":{"und":[{"tid":"171"}]}},{"title":"Peter Viereck","nid":"6021","type":"winner","changed":1439235136,"path_alias":"winners\/peter-viereck","field_abbr_citation":[],"field_category":{"und":[{"tid":"224"}]},"field_location_text":[],"field_publication":{"und":[{"safe_value":"Terror and Decorum\n"}]},"field_publisher":{"und":[{"safe_value":"Scribner\n"}]},"field_teaser_thumbnail":[],"field_year":{"und":[{"tid":"171"}]}},{"title":"Nebraska State Journal","nid":"6022","type":"winner","changed":1501605562,"path_alias":"winners\/nebraska-state-journal","field_abbr_citation":{"und":[{"safe_value":"For the campaign establishing the \u0026quot;Nebraska All-Star Primary\u0026quot; presidential preference primary which spotlighted, through a bi-partisan committee, issues early in the presidential campaign.\r\n"}]},"field_category":{"und":[{"tid":"204"}]},"field_location_text":[],"field_publication":[],"field_publisher":[],"field_teaser_thumbnail":[],"field_year":{"und":[{"tid":"171"}]}}]